zdpapi_ssh/__init__.py
zdpapi_ssh/ssh.py
zdpapi_ssh-0.1.2.dist-info/LICENSE
zdpapi_ssh-0.1.2.dist-info/WHEEL
zdpapi_ssh-0.1.2.dist-info/METADATA
zdpapi_ssh-0.1.2.dist-info/RECORD
