Metadata-Version: 2.1
Name: zdpapi-ssh
Version: 0.1.2
Summary: python实现ssh操作
Home-page: https://github.com/zhangdapeng520/zdpapi_ssh
License: MIT
Keywords: zdpapi,ssh,zhangdapeng
Author: 张大鹏
Author-email: lxgzhw@163.com
Requires-Python: >=3.8,<4.0
Classifier: License :: OSI Approved :: MIT License
Classifier: Programming Language :: Python :: 3
Classifier: Programming Language :: Python :: 3.8
Classifier: Programming Language :: Python :: 3.9
Requires-Dist: paramiko (>=2.8.1,<3.0.0)
Project-URL: Documentation, https://github.com/zhangdapeng520/zdpapi_ssh
Project-URL: Repository, https://github.com/zhangdapeng520/zdpapi_ssh
